paganini/__init__.py
paganini/expressions.py
paganini/specification.py
paganini/tests.py
paganini/tutorial.py
paganini/utils.py
paganini-1.3.2.dist-info/LICENSE
paganini-1.3.2.dist-info/METADATA
paganini-1.3.2.dist-info/WHEEL
paganini-1.3.2.dist-info/top_level.txt
paganini-1.3.2.dist-info/RECORD
