Metadata-Version: 2.1
Name: paganini
Version: 1.3.2
Summary: Multiparametric tuner for combinatorial specifications
Home-page: https://github.com/maciej-bendkowski/paganini
Author: Maciej Bendkowski, Sergey Dovgal
Author-email: maciej.bendkowski@tcs.uj.edu.pl, vit.north@gmail.com
License: BSD3
Platform: UNKNOWN
Requires-Dist: numpy
Requires-Dist: sympy
Requires-Dist: cvxpy
Requires-Dist: scipy
Requires-Dist: networkx
